mcts_llm/__init__.py
mcts_llm/logger.py
mcts_llm/mcts.py
mcts_llm/mctsr.py
mcts_llm/utils.py
mcts_llm-0.0.1.dist-info/LICENSE
mcts_llm-0.0.1.dist-info/METADATA
mcts_llm-0.0.1.dist-info/WHEEL
mcts_llm-0.0.1.dist-info/RECORD
