Metadata-Version: 2.1
Name: mcts-llm
Version: 0.0.1
Summary: MCTS + LLM + Prompt Engineering => Enhanced LLM Reponse Quality.
Home-page: https://github.com/numberchiffre/mcts-llm
License: MIT
Keywords: mcts,llm,dspy,prompt-engineering
Author: NumberChiffre
Author-email: llebox@hotmail.com
Requires-Python: >=3.12,<3.13
Classifier: License :: OSI Approved :: MIT License
Classifier: Operating System :: OS Independent
Classifier: Programming Language :: Python :: 3
Classifier: Programming Language :: Python :: 3.12
Requires-Dist: dspy-ai (==2.4.17)
Requires-Dist: python-dotenv (>=1.0.1,<2.0.0)
Project-URL: Bug Tracker, https://github.com/numberchiffre/mcts-llm/issues
Project-URL: Documentation, https://github.com/numberchiffre/mcts-llm#readme
Project-URL: Repository, https://github.com/numberchiffre/mcts-llm
